setup.cfg
setup.py
gel_coverage.egg-info/PKG-INFO
gel_coverage.egg-info/SOURCES.txt
gel_coverage.egg-info/dependency_links.txt
gel_coverage.egg-info/requires.txt
gel_coverage.egg-info/top_level.txt
gelcoverage/__init__.py
gelcoverage/constants.py
gelcoverage/runner.py
gelcoverage/tests.py
gelcoverage/stats/__init__.py
gelcoverage/stats/coverage_stats.py
gelcoverage/stats/sequence_stats.py
gelcoverage/stats/tests.py
gelcoverage/test/__init__.py
gelcoverage/test/output_verifier.py
gelcoverage/tools/__init__.py
gelcoverage/tools/backoff_retrier.py
gelcoverage/tools/bed_reader.py
gelcoverage/tools/bigwig_reader.py
gelcoverage/tools/cellbase_helper.py
gelcoverage/tools/panelapp_helper.py
gelcoverage/tools/tests.py
old/__init__.py
old/bw_exon_summary.py
old/gelCoveragePy.py
old/variant_coverage_summary.py
scripts/bed_maker
scripts/bigwig_analyser