Metadata-Version: 1.1
Name: gel-coverage
Version: 1.4.2
Summary: Whole genome coverage analysis tool
Home-page: https://github.com/genomicsengland/gel-coverage
Author: Pablo Riesgo Ferreiro
Author-email: pablo.riesgo-ferreiro@genomicsengland.co.uk
License: Apache
Download-URL: https://github.com/genomicsengland/gel-coverage/archive/v1.4.2.tar.gz
Platform: UNKNOWN
Classifier: Development Status :: 5 - Production/Stable
Classifier: Intended Audience :: Healthcare Industry
Classifier: Intended Audience :: Science/Research
Classifier: Topic :: Scientific/Engineering :: Bio-Informatics
Classifier: License :: OSI Approved :: Apache Software License
Classifier: Programming Language :: Python :: 2.7
Requires: pandas
Requires: pyBigWig
Requires: pybedtools
Requires: numpy
Requires: ujson
Requires: pycellbase
